{
  "WorkItem": {
    "AffectedComponent": {
      "Name": "",
      "DisplayName": ""
    },
    "ClosedComment": "",
    "ClosedDate": null,
    "CommentCount": 0,
    "Custom": null,
    "Description": "It would be nice if we see simple sync application (even like console).",
    "LastUpdatedDate": "2013-02-21T19:00:25.977-08:00",
    "PlannedForRelease": "",
    "ReleaseVisibleToPublic": false,
    "Priority": {
      "Name": "Low",
      "Severity": 50,
      "Id": 1
    },
    "ProjectName": "1code",
    "ReportedDate": "2011-02-05T06:27:13.177-08:00",
    "Status": {
      "Name": "Proposed",
      "Id": 1
    },
    "ReasonClosed": {
      "Name": "Unassigned"
    },
    "Summary": "Sync Framework sample",
    "Type": {
      "Name": "Issue",
      "Id": 3
    },
    "VoteCount": 7,
    "Id": 8301
  },
  "FileAttachments": [],
  "Comments": [
    {
      "Message": "Hello,\r\n\r\nThank you for using our code sample request service. \r\n\r\nI'd like to confirm with you my understanding of the sample request:\r\n\r\nYou said that It's really so simple. I don't know which scenario you have encounted. So I could repaint it in my brain. could you please describute it more clearly in order to settle using information for us. I'm glad that you make time to post sample request for us.\r\n\r\n\r\nThanks\r\nAll-In-One Code Framework\r\nhttp://1code.codeplex.com ",
      "PostedDate": "2011-03-13T19:57:34.3-07:00",
      "Id": -2147483648
    },
    {
      "Message": "",
      "PostedDate": "2011-07-18T15:50:57.46-07:00",
      "Id": -2147483648
    },
    {
      "Message": "",
      "PostedDate": "2011-08-01T02:38:07.8-07:00",
      "Id": -2147483648
    },
    {
      "Message": "",
      "PostedDate": "2012-01-19T04:27:10.63-08:00",
      "Id": -2147483648
    },
    {
      "Message": "",
      "PostedDate": "2013-02-21T19:00:25.977-08:00",
      "Id": -2147483648
    }
  ]
}