{
  "WorkItem": {
    "AffectedComponent": {
      "Name": "",
      "DisplayName": ""
    },
    "ClosedComment": "",
    "ClosedDate": null,
    "CommentCount": 0,
    "Custom": null,
    "Description": "I have a need to be able to open an excel 2010 macro enabled workbook from a Silverlight application and read data from a number of the sheets. I was able to do this with LiteExcel for Excel 2003 workbooks but it doesn't support the 2010 version.\n \nCan anyone help.",
    "LastUpdatedDate": "2013-02-21T18:59:07.4-08:00",
    "PlannedForRelease": "",
    "ReleaseVisibleToPublic": false,
    "Priority": {
      "Name": "Low",
      "Severity": 50,
      "Id": 1
    },
    "ProjectName": "1code",
    "ReportedDate": "2012-09-26T07:41:50.197-07:00",
    "Status": {
      "Name": "Proposed",
      "Id": 1
    },
    "ReasonClosed": {
      "Name": "Unassigned"
    },
    "Summary": "Read a sheet from .xlsm file with Silverlight",
    "Type": {
      "Name": "Issue",
      "Id": 3
    },
    "VoteCount": 1,
    "Id": 11227
  },
  "FileAttachments": [],
  "Comments": []
}