{
  "WorkItem": {
    "AffectedComponent": {
      "Name": "",
      "DisplayName": ""
    },
    "ClosedComment": "",
    "ClosedDate": null,
    "CommentCount": 0,
    "Custom": null,
    "Description": "A small C# VS 2010 port detector dll that is COM wrapped.  Exposes a CheckPort method with IPAddress and PortNumber parameters.  Returns PortInUse boolean property whether the port is currently in use or not.",
    "LastUpdatedDate": "2013-02-21T19:00:26.397-08:00",
    "PlannedForRelease": "",
    "ReleaseVisibleToPublic": false,
    "Priority": {
      "Name": "Low",
      "Severity": 50,
      "Id": 1
    },
    "ProjectName": "1code",
    "ReportedDate": "2011-02-03T14:23:06.91-08:00",
    "Status": {
      "Name": "Proposed",
      "Id": 1
    },
    "ReasonClosed": {
      "Name": "Unassigned"
    },
    "Summary": "Is Port In Use Detector - COM wrapped",
    "Type": {
      "Name": "Issue",
      "Id": 3
    },
    "VoteCount": 1,
    "Id": 8294
  },
  "FileAttachments": [],
  "Comments": [
    {
      "Message": "Hello,\r\n\r\nThank you for using our code sample request service. \r\n\r\nI'd like to confirm with you my understanding of the sample request:\r\n\r\nYou said the technology that I have used in previous sample coding. I think it could been solved by WMI or DDK ,and It's a good idea metioned in your topic.  Let's see how many people will vote for it. \r\n\r\nThanks\r\nAll-In-One Code Framework\r\nhttp://1code.codeplex.com ",
      "PostedDate": "2011-03-13T22:37:14.22-07:00",
      "Id": -2147483648
    },
    {
      "Message": "",
      "PostedDate": "2013-02-21T19:00:26.397-08:00",
      "Id": -2147483648
    }
  ]
}